carbonaware_ml/__init__.py
carbonaware_ml/cli.py
carbonaware_ml/logging_tb.py
carbonaware_ml/providers/__init__.py
carbonaware_ml/providers/base.py
carbonaware_ml/providers/electricity_maps.py
carbonaware_ml/providers/tou_ontario.py
carbonaware_ml/providers/watttime.py
carbonaware_ml/scheduler.py
carbonaware_ml/trainer.py
carbonaware_ml/utils.py
carbonaware_ml-0.1.1.dist-info/LICENSE
carbonaware_ml-0.1.1.dist-info/METADATA
carbonaware_ml-0.1.1.dist-info/WHEEL
carbonaware_ml-0.1.1.dist-info/entry_points.txt
carbonaware_ml-0.1.1.dist-info/RECORD
