Metadata-Version: 2.3
Name: carbonaware-ml
Version: 0.1.1
Summary: Carbon-aware PyTorch training plugin (multi-region via Electricity Maps/WattTime).
License: MIT License
Keywords: pytorch,carbon,sustainability,scheduling,electricity,carbon-aware,ml
Author: Carbon Aware ML Maintainers
Requires-Python: >=3.9
Classifier: Development Status :: 3 - Alpha
Classifier: Intended Audience :: Science/Research
Classifier: Intended Audience :: Developers
Classifier: Topic :: Scientific/Engineering :: Artificial Intelligence
Classifier: Topic :: Scientific/Engineering :: Information Analysis
Classifier: License :: OSI Approved :: MIT License
Classifier: Programming Language :: Python
Classifier: Programming Language :: Python :: 3
Classifier: Programming Language :: Python :: 3.9
Classifier: Programming Language :: Python :: 3.10
Classifier: Programming Language :: Python :: 3.11
Classifier: Programming Language :: Python :: 3.12
Classifier: Operating System :: OS Independent
Provides-Extra: all
Provides-Extra: scheduler
Provides-Extra: tensorboard
Requires-Dist: apscheduler (>=3.10.4) ; extra == "all"
Requires-Dist: apscheduler (>=3.10.4) ; extra == "scheduler"
Requires-Dist: requests (>=2.31.0)
Requires-Dist: tensorboard (>=2.12.0) ; extra == "all"
Requires-Dist: tensorboard (>=2.12.0) ; extra == "tensorboard"
Requires-Dist: torch (>=2.0.0)
Project-URL: Homepage, https://github.com/tomalmog/carbonaware-ml
Project-URL: Issues, https://github.com/tomalmog/carbonaware-ml/issues
Project-URL: Repository, https://github.com/tomalmog/carbonaware-ml
